widefield_analysis/__init__.py
widefield_analysis/animation.py
widefield_analysis/baseline.py
widefield_analysis/files.py
widefield_analysis/filter.py
widefield_analysis/resample.py
widefield_analysis/smooth.py
widefield_analysis/sta.py
widefield_analysis-0.1.6.dist-info/METADATA
widefield_analysis-0.1.6.dist-info/WHEEL
widefield_analysis-0.1.6.dist-info/RECORD
